<?xml version="1.0" encoding="UTF-8"?>
<resource>
	<text key="new">new</text>
	<text key="FrontDeviceList">FrontDeviceList</text>
	<text key="add">add</text>
	<text key="DataManagement">DataManagement</text>
	<text key="TrapConfig">TrapConfig</text>
	<text key="ConfigureNotification">ConfigureNotification</text>
	<text key="ConfigureWarnRegion">ConfigureWarnRegion</text>
	<text key="RegionManage">RegionManage</text>
	<text key="TimingMonitoringConfig">TimingMonitoringConfig</text>
	<text key="WarningManagement">WarningManagement</text>
	<text key="Layer3InterfaceTables">Layer3InterfaceTables</text>
	<text key="Layer2InterfaceTables">Layer2InterfaceTables</text>
	<text key="administrator">administrator</text>
	<text key="ConfigureGraphics">ConfigureGraphics</text>
	<text key="SwitcherManagement">SwitcherManagement</text>
	<text key="ExitSystem">ExitSystem</text>
	<text key="SaveConfig">SaveConfig</text>
	<text key="TopologyManagement">TopologyManagement</text>
	<text key="ConfigurePerformanceMonitor">ConfigurePerformanceMonitor</text>
	<text key="ConfigureSNMP">ConfigureSNMP</text>
	<text key="PingTool">PingTool</text>
	<text key="FrontEndManagement">FrontEndManagement</text>
	<text key="FrontEndExplorer">FrontEndExplorer</text>
	
	<text key="SearchDevice">SearchDevice</text>
	
	<text key="RouteTables">RouteTables</text>
	<text key="edit">edit</text>
	<text key="about">about</text>
	<text key="UserManagement">UserManagement</text>
	<text key="GPRS">GPRS</text>
	<text key="MIBBrowser">MIBBrowser</text>
	<text key="LockTopology">LockTopology</text>
	<text key="PrintTopology">PrintTopology</text>
	<text key="Emulation">Emulation</text>
	<text key="manual">manual</text>
	<text key="ConfigureFrontDevice">ConfigureFrontDevice</text>
	<text key="windows">windows</text>
	<text key="help">help</text>
	<text key="RSTPManage">RSTPManage</text>
	<text key="carrier">carrier</text>
	<text key="SystemManagement">SystemManagement</text>
	<text key="SeverMonitoring">SeverMonitoring</text>
	<text key="FDBTables">FDBTables</text>
	<text key="ARPTables">ARPTables</text>
	<text key="ConfigureTrap">ConfigureTrap</text>
	<text key="ConfigureVLAN">ConfigureVLAN</text>
	<text key="PortFlowLayer3">PortFlowLayer3</text>
	<text key="VLANManageLayer3">VLANManageLayer3</text>
	<text key="NetworkManagement">NetworkManagement</text>
	<text key="VLANManage">VLANManage</text>
	<text key="GHRingManage">WT-RingManage</text>
	<text key="SNMPManage">SNMPManage</text>
	<text key="SyslogManageView">SYSLOGManage</text>
	<text key="SubnetManagementView">SubnetManage</text>
	<text key="SwitcherUserManageView">SwitcherUserManage</text>
	<text key="FrontDeviceAuthentication">FrontDeviceAuthentication</text>
	<text key="ConfigureFaultDetection">ConfigureFaultDetection</text>
	<text key="FaultDetectionReport">FaultDetectionReport</text>
	<text key="ConfigPortWarning">ConfigPortWarning</text>
	<text key="DataReportExport">DataReportExport</text>
	<text key="FrontDeviceStatusMonitor">FrontDeviceStatusMonitor</text>
	<text key="RINGManage">RINGManage</text>
	<text key="ConfigurePort">ConfigurePort</text>
	<text key="ConfigureSubnet">ConfigureSubnet</text>
	<text key="PortManagement">PortManagement</text>
	<text key="EPONManagement">EPONManagement</text>
	<text key="OLTBaseInformation">OLTBaseInformation</text>
	<text key="OLTSlotInformateion">OLTSlotInformateion</text>
	<text key="OLTChipInformation">OLTChipInformation</text>
	<text key="OLTMulticast">OLTMulticast</text>
	<text key="OLTVlanConfiguration">OLTVlanConfiguration</text>
	<text key="OLTDBAInformation">OLTDBAInformation</text>
	<text key="ONUBaseInfo">ONUBaseInfo</text>
	<text key="OLTONUManagement">OLTONUManagement</text>
	<text key="OLTSTPConfiguration">OLTSTPConfiguration</text>
	<text key="OLTONUPortConfig">OLTONUPortConfig</text>
	<text key="ONULLIDCofnig">ONULLIDCofnig</text>
	<text key="EponEmulationView">EponEmulationView</text>
	<text key="OpticalSplitterBaseInfoView">OpticalSplitterBaseInfo</text>
	
	<text key="WarningTopTenInfoCategoryChart">WarningTopTenInfoCategoryChart</text>
	<text key="WarningInfoCategoryChart">WarningInfoCategoryChart</text>
	<text key="WarningInfoChartView">WarningInfoChart</text>
	<text key="QueryWarningHistoryView">QueryWarningHistoryView</text>
	<text key="QueryWarningRecord">QueryWarningRecord</text>
	<text key="QueryWarning">QueryWarning</text>
	<text key="NetworkManagement">NetworkManagement</text>
	<text key="ConfigureGIS">ConfigureGIS</text>
	<text key="PerformanceManagement">PerformanceManagement</text>
	<text key="RefreshTopology">RefreshTopology</text>
	<text key="ConfigureTopology">ConfigureTopology</text>
	<text key="VLANManagement">VLANManagement</text>
	<text key="MACConfiguration">MACConfiguration</text>
	<text key="MACUnicastConfiguration">MACUnicastConfiguration</text>
	<text key="MACMulticastConfiguration">MACMulticastConfiguration</text>
	<text key="GH-RINGManagement">WT-RINGManage</text>
	<text key="GH-RINGConfiguration">WT-RINGManage</text>
	<text key="STPConfiguration">STPConfiguration</text>
	<text key="SNTPConfiguration">SNTPConfiguration</text>
	<text key="IGMPConfiguration">IGMPConfiguration</text>
	<text key="LLDPConfiguration">LLDPConfiguration</text>
	<text key="QOSConfiguration">QoSConfiguration</text>
	<text key="RMONConfiguration">RMONConfiguration</text>
	<text key="SoftwareUpgrade">SoftwareUpgrade</text>
	<text key="SerialConfiguration">SerialConfiguration</text>
	<text key="BaseInfo">BaseInfo</text>
	<text key="IPAddress">IPAddress</text>
	<text key="UserConfiguration">UserConfiguration</text>
	<text key="Layer2Interface">Layer2Interface</text>
	<text key="Layer3Interface">Layer3Interface</text>
	<text key="Routetable">Routetable</text>
	<text key="ARPtable">ARPtable</text>
	<text key="Forwardtable">Forwardtable</text>
	<text key="GPRSManagement">GPRSManagement</text>
	<text key="NetworkUnit">NetworkUnit</text>
	<text key="NetworkElementManagement">NetworkElementManagement</text>
	<text key="SwitcherEmulation">SwitcherEmulation</text>
	<text key="DataSynchronization">DataSynchronization</text>
	<text key="LacpPortAggr">LacpPortAggr</text>
	<text key="MirrorPort">MirrorPort</text>
	<text key="TrunkPortAggr">TrunkPortAggr</text>
	<text key="PerformanceMonitorReport">PerformanceMonitorReport</text>
	<text key="MonitoringReport">MonitoringReport</text>
	<text key="EventConsole">EventConsole</text>
	<text key="Tools">Tools</text>
	<text key="Views">Views</text>
	<text key="GISTopo">GISTopo</text>
	<text key="CutlineView">CutlineView</text>
	<text key="Subnet">Subnet</text>
	<text key="Console">Console</text>
	<text key="EquipmentExplorer">EquipmentExplorer</text>
	<text key="EquipmentInfo">EquipmentInfo</text>
	<text key="CarrierManagement">CarrierManagement</text>
	<text key="CarrierInfo">CarrierInfo</text>
	<text key="ConfigureRoute">ConfigureRoute</text>
	<text key="ConfigurePort">ConfigurePort</text>
	<text key="SystemUpgrade">SystemUpgrade</text>
	<text key="CarrierSynRoute">CarrierSynRoute</text>
	<text key="ConfigureWaveBand">ConfigureWaveBand</text>
	<text key="ConfigureMonitor">ConfigureMonitor</text>
	<text key="MemoryMonitor">MemoryMonitor</text>
	<text key="ConfigureSystem">ConfigureSystem</text>
	<text key="ModifyPassword">ModifyPassword</text>
	<text key="MinimizeAllWindow">MinimizeAllWindow</text>
	<text key="RestoreAllWindow">RestoreAllWindow</text>
	<text key="CloseAllWindow">CloseAllWindow</text>
	<text key="RealtimePerformanceView">RealtimePerformanceView</text>
	<text key="PerformanceInfoSPLineChart">PerformanceInfoSPLineChart</text>
	<text key="save">save</text>
	<text key="close">close</text>
	<text key="delete">delete</text>
	
	<text key="EquipView_EquipExplorer">EquipExplorer</text>
	<text key="EquipView_Search">Search</text>
	<text key="EquipView_CompanyName">源拓</text>
	
	<text key="BaseInfoView_BaseInfo">BaseInfo</text>
	<text key="BaseInfoView_System">System</text>
	<text key="BaseInfoView_Contact">Contact</text>
	<text key="BaseInfoView_Hardware">Hardware</text>
	<text key="BaseInfoView_Time">Time</text>
	<text key="BaseInfoView_SoftWare">SoftWare</text>
	<text key="BaseInfoView_DeviceName">DeviceName</text>
	<text key="BaseInfoView_Address">Address</text>
	<text key="BaseInfoView_MACAddr">MACAddr</text>
	<text key="BaseInfoView_BootrotVersion">BootrotVersion</text>
	<text key="BaseInfoView_SystemTime">SystemTime</text>
	<text key="BaseInfoView_StartTime">StartTime</text>
	<text key="BaseInfoView_SoftWareVer">SoftWareVer</text>
	<text key="BaseInfoView_VerTime">VerTime</text>
	<text key="BaseInfoView_VerTime">VerTime</text>
	
	<text key="EVENT_CONSOLE_TITLE">EVENTTITLE</text>
	<text key="ALARM_COLUMN_RAISED_TIME">TIME</text>
	<text key="ALARM_COLUMN_SEVERITY">SEVERITY</text>
	<text key="ALARM_COLUMN_EQUIPMENT">FROM</text>
	<text key="ALARM_COLUMN_EQUIPMENT_TYPE">TYPE</text>
	<text key="ALARM_COLUMN_CONTENT">CONTENT</text>
	<text key="ALARM_COLUMN_EVENT">EVENT</text>
	<text key="ALARM_COLUMN_STATUS">STATUS</text>
	
	<text key="VlanView_VlanConfig">VLANConfig</text>
	<text key="VlanView_AddVlan">AddVlan</text>
	<text key="VlanView_VlanId">VLAN ID</text>
	<text key="VlanView_VlanName">VLAN Name</text>
	<text key="VlanView_PVID">PVID</text>
	<text key="VlanView_VlanList">VLAN List</text>
	<text key="VlanView_CurrentVlan">CurrentVLAN</text>
	<text key="VlanView_Id">ID</text>
	<text key="VlanView_Name">Name</text>
	<text key="VlanView_VlanOption">VLANOption</text>
	<text key="VlanView_VlanDetail">VLANDetail</text>
	<text key="VlanView_Port">Port</text>
	<text key="VlanView_Mark">Mark</text>
	<text key="VlanView_Priority">Priority</text>
	
	<text key="begin_action_text">begin</text>
	<text key="start_action_text">start</text>
	<text key="stop_action_text">stop</text>
	<text key="disabled_action_text">disabled</text>
	<text key="append_action_text">append</text>
	<text key="refresh_action_text">refresh</text>
	<text key="save_action_text">save</text>
	<text key="close_action_text">close</text>
	<text key="delete_action_text">delete</text>
	<text key="synchronize_action_text">synchronize</text>
	<text key="modify_action_text">modify</text>
	<text key="clean_action_text">clean</text>
	<text key="query_action_text">query</text>
	<text key="test_action_text">test</text>
	<text key="restart_action_text">restart</text>
	<text key="send_action_text">send</text>
	<text key="ok_action_text">ok</text>
	<text key="loadMib_action_text">loadMib</text>
	<text key="removeMib_action_text">removeMib</text>
	<text key="config_action_text">config</text>
	<text key="back_action_text">back</text>

	<text key="import_action_text">import</text>
	<text key="export_action_text">export</text>
	<text key="upload_action_text">upload</text>
	<text key="download_action_text">download</text>
	<text key="upload_action_text">upload</text>
	<text key="download_action_text">download</text>
	<text key="play_action_text">play</text>
	<text key="confirm_action_text">confirm</text>
	<text key="advancedQuery_action_text">advancedQuery</text>
	<text key="deleteIP_action_text">deleteIP</text>
	
	<text key="search_action_text">search</text>
	
	<text key="first_action_text">first</text>
	<text key="previous_action_text">previous</text>
	<text key="next_action_text">next</text>
	<text key="last_action_text">last</text>
	
	<text key="closeAlarm_action_text">closeAlarm</text>
	<text key="fixAlarm_action_text">fixAlarm</text>
	<text key="WarningAudioConfigure">WarningAudioConfigure</text>
	
	<!-- Amend 2010.06.22 -->
	<text key="LOG_USER_NAME">USER_NAME</text>
	<text key="LOG_CONTENTS">CONTENTS</text>
	<text key="LOG_DO_TIME">DO_TIME</text>
	<text key="LOG_CLIENT_IP">CLIENT_IP</text>
	<text key="LogManagement">LogManagement</text>
	
	<text key="Warning_record_message">message</text>
	<text key="Warning_record_do_time">time</text>
	<text key="Warning_record_system_ip">system_ip</text>
	<text key="Warning_record_accepter">accepter</text>
	<text key="Warning_record_warningStyle">warningStyle</text>
	
	<text key="MONITOR_EQUIPMENT">MONITOR_EQUIPMENT</text>
	<text key="MONITOR_PORT">MONITOR_PORT</text>
	<text key="PARAM">PARAM</text>
	<text key="START_TIME">START_TIME</text>
	<text key="END_TIME">END_TIME</text>
	
	<text key="TIME">TIME</text>
	<text key="EQUIPMENT">EQUIPMENT</text>
	<text key="PORT">PORT</text>
	<text key="PARAM">PARAM</text>
	<text key="VALUE">VALUE</text>
	
	<text key="PORT_NUM">PORT_NUM</text>
	<text key="PORT_TYPE">PORT_TYPE</text>
	<text key="IPVALUE">IPVALUE</text>
	<text key="SLOT">SLOT</text>
	
	<text key="SUBNET_NAME">SUBNET_NAME</text>
	
	<text key="Layer3Switcher">Layer3Switcher</text>
	<text key="LicenseManagement">LicenseManagement</text>
	<text key="NetworkTypeManagement">NetworkTypeManagement</text>
</resource>